LICENSE
MANIFEST.in
README.rst
gerrit_growler.py
setup.py
gerrit_growler.egg-info/PKG-INFO
gerrit_growler.egg-info/SOURCES.txt
gerrit_growler.egg-info/dependency_links.txt
gerrit_growler.egg-info/entry_points.txt
gerrit_growler.egg-info/requires.txt
gerrit_growler.egg-info/top_level.txt