Metadata-Version: 1.1
Name: gerrit-growler
Version: 1.0.1
Summary: Receive growl notifications from Gerrit.
Home-page: http://github.com/dolph/gerrit-growler
Author: Dolph Mathews
Author-email: dolph.mathews@gmail.com
License: UNKNOWN
Platform: UNKNOWN
Classifier: Development Status :: 5 - Production/Stable
Classifier: Environment :: Console
Classifier: Intended Audience :: Developers
Classifier: Topic :: Utilities
